manimx/__init__.py
manimx/__main__.py
manimx/config.py
manimx/constants.py
manimx/default_config.yml
manimx/extract_scene.py
manimx/logger.py
manimx/shader_wrapper.py
manimx/tex_templates.yml
manimx/typing.py
manimx/window.py
manimx/animation/__init__.py
manimx/animation/animation.py
manimx/animation/composition.py
manimx/animation/creation.py
manimx/animation/fading.py
manimx/animation/growing.py
manimx/animation/indication.py
manimx/animation/movement.py
manimx/animation/numbers.py
manimx/animation/rotation.py
manimx/animation/specialized.py
manimx/animation/transform.py
manimx/animation/transform_matching_parts.py
manimx/animation/update.py
manimx/camera/__init__.py
manimx/camera/camera.py
manimx/camera/camera_frame.py
manimx/event_handler/__init__.py
manimx/event_handler/event_dispatcher.py
manimx/event_handler/event_listner.py
manimx/event_handler/event_type.py
manimx/mobject/__init__.py
manimx/mobject/boolean_ops.py
manimx/mobject/changing.py
manimx/mobject/coordinate_systems.py
manimx/mobject/frame.py
manimx/mobject/functions.py
manimx/mobject/geometry.py
manimx/mobject/interactive.py
manimx/mobject/matrix.py
manimx/mobject/mobject.py
manimx/mobject/mobject_update_utils.py
manimx/mobject/number_line.py
manimx/mobject/numbers.py
manimx/mobject/probability.py
manimx/mobject/shape_matchers.py
manimx/mobject/three_dimensions.py
manimx/mobject/value_tracker.py
manimx/mobject/vector_field.py
manimx/mobject/svg/__init__.py
manimx/mobject/svg/brace.py
manimx/mobject/svg/drawings.py
manimx/mobject/svg/old_tex_mobject.py
manimx/mobject/svg/special_tex.py
manimx/mobject/svg/string_mobject.py
manimx/mobject/svg/svg_mobject.py
manimx/mobject/svg/tex_mobject.py
manimx/mobject/svg/text_mobject.py
manimx/mobject/types/__init__.py
manimx/mobject/types/dot_cloud.py
manimx/mobject/types/image_mobject.py
manimx/mobject/types/point_cloud_mobject.py
manimx/mobject/types/surface.py
manimx/mobject/types/vectorized_mobject.py
manimx/scene/__init__.py
manimx-2024.6.22.dist-info/LICENSE
manimx-2024.6.22.dist-info/METADATA
manimx-2024.6.22.dist-info/WHEEL
manimx-2024.6.22.dist-info/entry_points.txt
manimx-2024.6.22.dist-info/top_level.txt
manimx-2024.6.22.dist-info/RECORD
