Metadata-Version: 2.1
Name: manimx
Version: 2024.6.22
Summary: Animation engine for explanatory math videos
Home-page: https://github.com/Manim-X/manimx
Author: Mark Hoo
Author-email: markhoo@foxmail.com
License: MIT
Project-URL: Bug Tracker, https://github.com/Manim-X/manimx/issues
Project-URL: Documentation, https://manim-x.github.io/manimx/
Project-URL: Source Code, https://github.com/Manim-X/manimx
Classifier: Development Status :: 4 - Beta
Classifier: License :: OSI Approved :: MIT License
Classifier: Topic :: Scientific/Engineering
Classifier: Topic :: Multimedia :: Video
Classifier: Topic :: Multimedia :: Graphics
Classifier: Programming Language :: Python :: 3.8
Classifier: Programming Language :: Python :: 3.9
Classifier: Programming Language :: Python :: 3.10
Classifier: Programming Language :: Python :: 3.11
Classifier: Programming Language :: Python :: 3.12
Classifier: Programming Language :: Python :: 3 :: Only
Classifier: Natural Language :: English
License-File: LICENSE
Requires-Dist: colour <=0.1.5
Requires-Dist: ipython <=8.24.0
Requires-Dist: isosurfaces <=0.1.2
Requires-Dist: manimpango <0.5.0,>=0.4.0.post0
Requires-Dist: mapbox-earcut <=1.0.1
Requires-Dist: matplotlib <=3.9.0
Requires-Dist: moderngl <=5.10.0
Requires-Dist: moderngl-window <=2.4.6
Requires-Dist: numpy <=1.26.4
Requires-Dist: Pillow <=10.3.0
Requires-Dist: pydub <=0.25.1
Requires-Dist: pygments <=2.18.0
Requires-Dist: PyOpenGL <=3.1.7
Requires-Dist: pyperclip <=1.8.2
Requires-Dist: pyyaml <=6.0.1
Requires-Dist: rich <=13.7.1
Requires-Dist: scipy <=1.13.1
Requires-Dist: screeninfo <=0.8.1
Requires-Dist: skia-pathops <=0.8.0.post1
Requires-Dist: svgelements >=1.8.1
Requires-Dist: sympy <=1.12
Requires-Dist: tqdm <=4.66.4
Requires-Dist: validators <=0.28.3
